[{"user_id":"7","full_name":"A. K. Krishnamurthy","first_name":"A. K.","last_name":"Krishnamurthy","email":"Amurthy@sort.com","create_date":"2020-04-24 15:45:54","address_id":"7","address_user_id":"7","house_no":"1572A","street":"Hawai Street","zipcode":"19ns8","address_city_id":"19","city_id":"19","city_name":"Michigan"},{"user_id":"8","full_name":"Aamir khan","first_name":"Aamir","last_name":"khan","email":"a@khan.com","create_date":"2020-04-24 15:46:35","address_id":"8","address_user_id":"8","house_no":"618","street":"Dalal Street","zipcode":"712bsk","address_city_id":"7","city_id":"7","city_name":"Connecticut"},{"user_id":"4","full_name":"Alex parsons","first_name":"Alex","last_name":"parsons","email":"parsonalex@test.com","create_date":"2020-04-24 15:42:25","address_id":"4","address_user_id":"4","house_no":"727","street":"Street 123","zipcode":"Ahjusbah","address_city_id":"28","city_id":"28","city_name":"Washington"},{"user_id":"6","full_name":"Buddha dev Mondal","first_name":"Buddha dev","last_name":"Mondal","email":"bomondal@pos.com","create_date":"2020-04-24 15:45:03","address_id":"6","address_user_id":"6","house_no":"D-93, First Floor","street":"sector 52","zipcode":"22017","address_city_id":"20","city_id":"20","city_name":"Nevada"},{"user_id":"9","full_name":"Fernandes Benjamin","first_name":"Fernandes","last_name":"Benjamin","email":"bfran@bski.com","create_date":"2020-04-24 15:47:55","address_id":"9","address_user_id":"9","house_no":"527","street":"Hawa Hawa","zipcode":"92bjd","address_city_id":"15","city_id":"15","city_name":"Kansas"},{"user_id":"11","full_name":"Harappa Kumar","first_name":"Harappa","last_name":"Kumar","email":"hk@hk.sdb","create_date":"2020-04-24 16:03:25","address_id":"11","address_user_id":"11","house_no":"A 3\/3","street":"St. John's","zipcode":"211A","address_city_id":"17","city_id":"17","city_name":"Maryland"},{"user_id":"5","full_name":"Ikhlakh Khan","first_name":"Ikhlakh","last_name":"Khan","email":"ikhlakhkhan@specialop.com","create_date":"2020-04-24 15:44:13","address_id":"5","address_user_id":"5","house_no":"A, 102","street":"Al jawahar","zipcode":"12814","address_city_id":"8","city_id":"8","city_name":"Delaware"},{"user_id":"2","full_name":"John Doe","first_name":"John","last_name":"Doe","email":"jdoe@nsk.coj","create_date":"2020-04-24 15:40:33","address_id":"2","address_user_id":"2","house_no":"11 h no","street":"Fl street","zipcode":"S4181","address_city_id":"9","city_id":"9","city_name":"Florida"},{"user_id":"10","full_name":"Louis Philip","first_name":"Louis","last_name":"Philip","email":"lphilip@lp.com","create_date":"2020-04-24 16:02:12","address_id":"10","address_user_id":"10","house_no":"A 2\/4","street":"R P Street","zipcode":"110021","address_city_id":"6","city_id":"6","city_name":"Colorado"},{"user_id":"3","full_name":"Saint Smith","first_name":"Saint","last_name":"Smith","email":"ssmith@mydomain.com","create_date":"2020-04-24 15:41:45","address_id":"3","address_user_id":"3","house_no":"715, tower a","street":"Street of atlant","zipcode":"36wj","address_city_id":"10","city_id":"10","city_name":"Georgia"},{"user_id":"1","full_name":"Sameer Agarwal","first_name":"Sameer","last_name":"Agarwal","email":"corporate.sameeragarwal@gmail.com","create_date":"2020-04-24 15:39:57","address_id":"1","address_user_id":"1","house_no":"H 1403","street":"Pan Oasis, Sector 70","zipcode":"201301","address_city_id":"11","city_id":"11","city_name":"Hawaii"},{"user_id":"12","full_name":"Test user","first_name":"Test","last_name":"user","email":"uertest@test.com","create_date":"2020-04-24 16:05:21","address_id":"12","address_user_id":"12","house_no":"ABC 123","street":"11, AAvhsa","zipcode":"62bjd","address_city_id":"11","city_id":"11","city_name":"Hawaii"}]